hicciexceptions/__init__.py
hicciexceptions/cci_exceptions.py
hicciexceptions-1.0.0.dist-info/LICENSE
hicciexceptions-1.0.0.dist-info/METADATA
hicciexceptions-1.0.0.dist-info/WHEEL
hicciexceptions-1.0.0.dist-info/top_level.txt
hicciexceptions-1.0.0.dist-info/RECORD
